README.md
setup.py
desantis/__init__.py
desantis.egg-info/PKG-INFO
desantis.egg-info/SOURCES.txt
desantis.egg-info/dependency_links.txt
desantis.egg-info/not-zip-safe
desantis.egg-info/top_level.txt