Metadata-Version: 1.0
Name: desantis
Version: 0.1
Summary: desantis
Home-page: https://github.com/desantis/python-desantis
Author: Andrew T. DeSantis
Author-email: atd@deos.org
License: MIT
Platform: UNKNOWN
